bohm/__init__.py
bohm/ensemble.py
bohm/state.py
bohm/traj.py
bohm/velocity.py
bohm/version.py
bohm-0.0.1a1.dist-info/DESCRIPTION.rst
bohm-0.0.1a1.dist-info/METADATA
bohm-0.0.1a1.dist-info/RECORD
bohm-0.0.1a1.dist-info/WHEEL
bohm-0.0.1a1.dist-info/metadata.json
bohm-0.0.1a1.dist-info/top_level.txt
