Metadata-Version: 2.0
Name: bohm
Version: 0.0.1a1
Summary: UNKNOWN
Home-page: UNKNOWN
Author: sahn
Author-email: jam31118@gmail.com
License: MIT
Keywords: physics
Platform: UNKNOWN
Classifier: Topic :: Scientific/Engineering :: Physics
Classifier: Topic :: Scientific/Engineering :: Visualization
Classifier: License :: OSI Approved :: MIT License
Classifier: Programming Language :: Python :: 3.5
Classifier: Programming Language :: Python :: 3.6
Requires-Dist: numpy
Requires-Dist: matplotlib
Requires-Dist: scipy
Requires-Dist: ntype
Requires-Dist: tdse
Requires-Dist: qprop
